simple_framework/__init__.py
simple_framework/simple_framework.py
your_unique_simple_framework-0.1.2.dist-info/METADATA
your_unique_simple_framework-0.1.2.dist-info/WHEEL
your_unique_simple_framework-0.1.2.dist-info/top_level.txt
your_unique_simple_framework-0.1.2.dist-info/RECORD
