Metadata-Version: 2.1
Name: your-unique-simple-framework
Version: 0.1.2
Summary: A simple web framework for Python
Home-page: https://github.com/yourusername/simple-framework
Author: Your Name
Author-email: your.email@example.com
Classifier: Programming Language :: Python :: 3
Classifier: License :: OSI Approved :: MIT License
Classifier: Operating System :: OS Independent
Requires-Python: >=3.6
Requires-Dist: Jinja2 >=3.0.0
Requires-Dist: watchdog >=2.1.0
